pyui/__init__.py
pyui/animation.py
pyui/app.py
pyui/asset.py
pyui/env.py
pyui/font.py
pyui/geom.py
pyui/state.py
pyui/theme.py
pyui/utils.py
pyui/data/icons.json
pyui/fonts/dejavu/DejaVuMathTeXGyre.ttf
pyui/fonts/dejavu/DejaVuSans-Bold.ttf
pyui/fonts/dejavu/DejaVuSans-BoldOblique.ttf
pyui/fonts/dejavu/DejaVuSans-ExtraLight.ttf
pyui/fonts/dejavu/DejaVuSans-Oblique.ttf
pyui/fonts/dejavu/DejaVuSans.ttf
pyui/fonts/dejavu/DejaVuSansCondensed-Bold.ttf
pyui/fonts/dejavu/DejaVuSansCondensed-BoldOblique.ttf
pyui/fonts/dejavu/DejaVuSansCondensed-Oblique.ttf
pyui/fonts/dejavu/DejaVuSansCondensed.ttf
pyui/fonts/dejavu/DejaVuSansMono-Bold.ttf
pyui/fonts/dejavu/DejaVuSansMono-BoldOblique.ttf
pyui/fonts/dejavu/DejaVuSansMono-Oblique.ttf
pyui/fonts/dejavu/DejaVuSansMono.ttf
pyui/fonts/dejavu/DejaVuSerif-Bold.ttf
pyui/fonts/dejavu/DejaVuSerif-BoldItalic.ttf
pyui/fonts/dejavu/DejaVuSerif-Italic.ttf
pyui/fonts/dejavu/DejaVuSerif.ttf
pyui/fonts/dejavu/DejaVuSerifCondensed-Bold.ttf
pyui/fonts/dejavu/DejaVuSerifCondensed-BoldItalic.ttf
pyui/fonts/dejavu/DejaVuSerifCondensed-Italic.ttf
pyui/fonts/dejavu/DejaVuSerifCondensed.ttf
pyui/fonts/dejavu/LICENSE
pyui/fonts/fontawesome/LICENSE.txt
pyui/fonts/fontawesome/brands.otf
pyui/fonts/fontawesome/regular.otf
pyui/fonts/fontawesome/solid.otf
pyui/themes/dark/config.json
pyui/themes/dark/assets/button.png
pyui/themes/dark/assets/button_pressed.png
pyui/themes/dark/assets/button_primary.png
pyui/themes/dark/assets/button_primary_pressed.png
pyui/themes/dark/assets/checkbox.png
pyui/themes/dark/assets/checkbox_checked.png
pyui/themes/dark/assets/checkbox_checked_pressed.png
pyui/themes/dark/assets/checkbox_pressed.png
pyui/themes/dark/assets/focus.png
pyui/themes/dark/assets/hscroll_track.png
pyui/themes/dark/assets/menu.png
pyui/themes/dark/assets/progress_bar.png
pyui/themes/dark/assets/progress_track.png
pyui/themes/dark/assets/scroll_corner.png
pyui/themes/dark/assets/scroll_knob.png
pyui/themes/dark/assets/segment_center.png
pyui-0.1.0.dist-info/LICENSE
pyui-0.1.0.dist-info/METADATA
pyui-0.1.0.dist-info/WHEEL
pyui-0.1.0.dist-info/top_level.txt
pyui-0.1.0.dist-info/RECORD
