Metadata-Version: 2.1
Name: pyui
Version: 0.1.0
Summary: A declarative GUI framework for Python using PySDL2.
Home-page: https://github.com/dcwatson/pyui
Author: Dan Watson
Author-email: dcwatson@gmail.com
License: BSD
Project-URL: Documentation, https://pyui.net
Classifier: Development Status :: 3 - Alpha
Classifier: Intended Audience :: Developers
Classifier: License :: OSI Approved :: MIT License
Classifier: Programming Language :: Python
Classifier: Programming Language :: Python :: 3
Classifier: Topic :: Software Development :: User Interfaces
License-File: LICENSE
Requires-Dist: PySDL2 (>=0.9.7)
